hood/__init__.py
hood/py.typed
hood/crypto_trading/__init__.py
hood/crypto_trading/_protocols.py
hood/crypto_trading/auth.py
hood/crypto_trading/constants.py
hood/crypto_trading/parse.py
hood/crypto_trading/structures.py
hood/crypto_trading/util.py
hood/crypto_trading/_endpoint/__init__.py
hood/crypto_trading/_endpoint/account.py
hood/crypto_trading/_endpoint/market.py
hood/crypto_trading/_endpoint/trading.py
hood/crypto_trading/schema/__init__.py
hood/crypto_trading/schema/account.py
hood/crypto_trading/schema/market.py
hood/crypto_trading/schema/trading.py
hood-0.1.0.dist-info/licenses/LICENSE
hood-0.1.0.dist-info/METADATA
hood-0.1.0.dist-info/WHEEL
hood-0.1.0.dist-info/top_level.txt
hood-0.1.0.dist-info/RECORD
