Metadata-Version: 2.4
Name: hood
Version: 0.1.0
Summary: Unofficial library for the Robinhood Crypto Trading API
Author-email: Jayson Fong <jayson.fong@gatech.edu>
License-Expression: MIT
Project-URL: Homepage, https://github.com/Jayson-Fong/hood
Project-URL: Issues, https://github.com/Jayson-Fong/hood/issues
Requires-Python: >=3.8
License-File: LICENSE
Requires-Dist: requests>=2.32.4
Requires-Dist: PyNaCl>=1.6.2
Dynamic: license-file
